{
    "BpbEnabled": {
        "description": "BTI mitigations supported and enabled"
    },
    "BpbDisabledSystemPolicy": {
        "description": "BTI mitigations disabled by system policy",
        "invert": true
    },
    "BpbDisabledNoHardwareSupport": {
        "description": "BTI mitigations disabled due to missing hardware support",
        "invert": true
    },
    "SpecCtrlEnumerated": {
        "description": "Processor supports IA32_SPEC_CTRL (Speculation Control) MSR"
    },
    "SpecCmdEnumerated": {
        "description": "Processor supports IA32_PRED_CMD (Prediction Command) MSR"
    },
    "IbrsPresent": {
        "description": "Processor supports IBRS"
    },
    "StibpPresent": {
        "description": "Processor supports STIBP"
    },
    "SmepPresent": {
        "description": "Processor supports SMEP"
    },
    "SpeculativeStoreBypassDisableAvailable": {
        "description": "OS supports SSBD"
    },
    "SpeculativeStoreBypassDisableSupported": {
        "description": "Processor supports SSBD"
    },
    "SpeculativeStoreBypassDisabledSystemWide": {
        "description": "SSBD disabled system-wide",
        "invert": true
    },
    "SpeculativeStoreBypassDisabledKernel": {
        "description": "[TODO] SSBD disabled for kernel-mode transitions",
        "invert": true
    },
    "SpeculativeStoreBypassDisableRequired": {
        "description": "Processor is vulnerable to SSB (Spectre-NG V4)",
        "invert": true
    },
    "BpbDisabledKernelToUser": {
        "description": "BTI mitigations disabled for kernel to user-mode transitions",
        "invert": true
    },
    "SpecCtrlRetpolineEnabled": {
        "description": "Retpoline mitigation enabled for compatible drivers"
    },
    "SpecCtrlImportOptimizationEnabled": {
        "description": "Retpoline mitigation import address table optimisation enabled"
    },
    "EnhancedIbrs": {
        "description": "Processor supports EIBRS"
    },
    "HvL1tfStatusAvailable": {
        "description": "OS supports L1TF VMM vulnerability mitigation"
    },
    "HvL1tfProcessorNotAffected": {
        "description": "Processor unaffected by L1TF VMM vulnerability"
    },
    "HvL1tfMigitationEnabled": {
        "description": "L1TF VMM vulnerability mitigation enabled"
    },
    "HvL1tfMigitationNotEnabled_Hardware": {
        "description": "L1TF VMM mitigation disabled due to missing hardware support",
        "invert": true
    },
    "HvL1tfMigitationNotEnabled_LoadOption": {
        "description": "L1TF VMM mitigation disabled by hypervisor load option",
        "invert": true
    },
    "HvL1tfMigitationNotEnabled_CoreScheduler": {
        "description": "L1TF VMM mitigation not required due to use of Core scheduler"
    },
    "EnhancedIbrsReported": {
        "description": "OS supports EIBRS"
    },
    "MdsHardwareProtected": {
        "description": "Processor unaffected by MDS vulnerabilities"
    },
    "MbClearEnabled": {
        "description": "MDS vulnerability mitigations enabled"
    },
    "MbClearReported": {
        "description": "OS supports MDS vulnerability mitigations"
    },
    // TODO
    "TsxCtrlStatus1": {
        "description": "TSX RTM feature disabled (XBEGIN instruction)"
    },
    // TODO
    "TsxCtrlStatus2": {
        "description": "TSX RTM & HLE feature enumeration disabled"
    },
    "TsxCtrlReported": {
        "description": "OS supports TAA vulnerability mitigation"
    },
    "TaaHardwareImmune": {
        "description": "Processor unaffected by TAA vulnerability"
    },
    "SbdrSsdpHardwareProtected": {
        "description": "Processor unaffected by SBDR vulnerability"
    },
    "FbsdpHardwareProtected": {
        "description": "Processor unaffected by FBSDP vulnerability [TODO Dynalist]"
    },
    "PsdpHardwareProtected": {
        "description": "Processor unaffected by PSDP vulnerability [TODO Dynalist]"
    },
    "FbClearEnabled": {
        "description": "MMIO Stale Data vulnerability mitigations enabled"
    },
    "FbClearReported": {
        "description": "OS supports MMIO Stale Data vulnerability mitigations"
    },
    "BhbEnabled": {
        "description": "BHB mitigation supported and enabled"
    },
    "BhbDisabledSystemPolicy": {
        "description": "BHB mitigation disabled by system policy"
    },
    "BhbDisabledNoHardwareSupport": {
        "description": "BHB mitigation disabled due to missing hardware support"
    },
    "BranchConfusionStatus": {
        "description": "TODO"
    },
    "BranchConfusionReported": {
        "description": "TODO"
    },
    "RdclHardwareProtectedReported": {
        "description": "TODO"
    },
    "RdclHardwareProtected": {
        "description": "Processor unaffected by RDCL vulnerability"
    },
    "GdsReported": {
        "description": "TODO"
    },
    "GdsStatus": {
        "description": "TODO"
    },
    "SrsoReported": {
        "description": "TODO"
    },
    "SrsoStatus": {
        "description": "TODO"
    },
    "DivideByZeroReported": {
        "description": "TODO"
    },
    "DivideByZeroStatus": {
        "description": "TODO"
    },
    "RfdsReported": {
        "description": "TODO"
    },
    "RfdsStatus": {
        "description": "TODO"
    }
}
